z30lib/files.py
z30lib/http.py
z30lib/installer.py
z30lib/ip.py
z30lib/modules.py
z30lib/platform.py
z30lib-1.0.5.dist-info/METADATA
z30lib-1.0.5.dist-info/WHEEL
z30lib-1.0.5.dist-info/top_level.txt
z30lib-1.0.5.dist-info/RECORD
