Metadata-Version: 2.4
Name: z30lib
Version: 1.0.5
Summary: A cross-platform system & hardware information library by Z30-Development
Author: Z30-Development
Project-URL: Homepage, https://github.com/Z30-Development/z30lib
Project-URL: Issue tracker, https://github.com/Z30-Development/z30lib/issues
Classifier: Development Status :: 4 - Beta
Classifier: License :: OSI Approved :: MIT License
Classifier: Intended Audience :: Developers
Classifier: Natural Language :: English
Classifier: Operating System :: OS Independent
Classifier: Programming Language :: Python :: 3.10
Classifier: Programming Language :: Python :: 3.11
Classifier: Programming Language :: Python :: 3.12
Classifier: Topic :: Software Development :: Libraries
Classifier: Topic :: System :: Operating System
Classifier: Topic :: Utilities
Classifier: Typing :: Typed
Requires-Python: >=3.10
Requires-Dist: requests
Requires-Dist: netifaces
Requires-Dist: speedtest-cli
Requires-Dist: psutil
Requires-Dist: py-cpuinfo
Requires-Dist: wmi; platform_system == "Windows"
Requires-Dist: distro; platform_system == "Linux"
Provides-Extra: network
Requires-Dist: netifaces; extra == "network"
Provides-Extra: speedtest
Requires-Dist: speedtest-cli; extra == "speedtest"
